asyncrd/__init__.py
asyncrd/connection.py
asyncrd/exceptions.py
asyncrd/protocol.py
asyncrd/query.py
asyncrd-2.1.7.dist-info/LICENSE
asyncrd-2.1.7.dist-info/METADATA
asyncrd-2.1.7.dist-info/WHEEL
asyncrd-2.1.7.dist-info/top_level.txt
asyncrd-2.1.7.dist-info/RECORD
